drb_impl_netcdf/__init__.py
drb_impl_netcdf/_version.py
drb_impl_netcdf/cortex.yml
drb_impl_netcdf/execptions.py
drb_impl_netcdf/netcdf_common.py
drb_impl_netcdf/netcdf_dimension_node.py
drb_impl_netcdf/netcdf_group_node.py
drb_impl_netcdf/netcdf_list_node.py
drb_impl_netcdf/netcdf_node_factory.py
drb_impl_netcdf/netcdf_variable_node.py
drb_impl_netcdf-1.0.5.data/data/requirements.txt
drb_impl_netcdf-1.0.5.dist-info/METADATA
drb_impl_netcdf-1.0.5.dist-info/WHEEL
drb_impl_netcdf-1.0.5.dist-info/entry_points.txt
drb_impl_netcdf-1.0.5.dist-info/top_level.txt
drb_impl_netcdf-1.0.5.dist-info/RECORD
